pascrd/__init__.py
pascrd/utils.py
pascrd/api/__init__.py
pascrd/api/human_cell_atlas.py
pascrd/api/tabula_sapiens.py
pascrd/api/data/__init__.py
pascrd/api/data/hca.json
tests/__init__.py
tests/test_basic_parsers.py
pascrd-0.1.0.dist-info/METADATA
pascrd-0.1.0.dist-info/WHEEL
pascrd-0.1.0.dist-info/top_level.txt
pascrd-0.1.0.dist-info/RECORD
